bin/farapy.py
farapy-1.33.2.dist-info/METADATA
farapy-1.33.2.dist-info/WHEEL
farapy-1.33.2.dist-info/entry_points.txt
farapy-1.33.2.dist-info/top_level.txt
farapy-1.33.2.dist-info/RECORD
